{
	"en" : {
		"map" : "Map",
		"wlsinmap" : "WLs in map",
		"wallbreach" : "Wall Breach",
		"farm" : "Farm",
		"teleporter" : "Teleporter",
		"prophack" : "Prop Hack",
		"openui" : "Open UI",
		"spells" : "Spells",
		"fun" : "Fun!",
		"wings" : "Wings",
		"nowindwall" : "No Wind Wall",
		"otherhacks" : "Other Hacks",
		"settings" : "Settings",
		"currentmap" : "Current Map",
		"semiautocr" : "Semi-AutoCR",
		"tptowl" : "Teleport to WL",
		"tpwltoy" : "Teleport WLs to yourself",
		"tpsttoy" : "Teleport Statues to yourself",
		"collectwaxes" : "Collect Waxes",
		"collectwls" : "Collect WLs",
		"unlockelders" : "Unlock Elders",
		"changemap" : "Change Map",
		"goto" : "Go to...",
		"openui2" : "Open UI",
		"closet" : "Closet",
		"constellation" : "Constellation (buggy)",
		"funstuff" : "Fun Stuffs",
		"infinityfireworks" : "Infinity Fireworks",
		"fakesleeping" : "Fake Sleeping",
		"walkwithinstrument" : "Walk with Instrument",
		"readchats" : "Read Chats",
		"wlcount" : "WL count",
		"setwlcount" : "Set WL count",
		"throwwl" : "Throw WLs ⚠️",
		"explodewl" : "Explode WLs ⚠️",
		"selecthacks" : "Select Hacks",
		"autoburn" : "Autoburn",
		"uacae" : "Unlock All Cosmetics and Emotes",
		"ufn" : "Unlock Friend Nodes",
		"unlimitedenergy" : "Unlimited Energy",
		"quicksteps" : "Quick Steps",
		"removeclouds" : "Remove Clouds",
		"wbd" : "Wall Breach distance",
		"uaiacr" : "Use Autoburn in AutoCR",
		"showpcoords" : "Show player coords in menu title",
		"noproprecharge" : "Remove prop recharge",
		"tpmenuaftercr" : "\"Teleport\" menu after AutoCR",
		"ggvisible" : "GG visible",
		"language" : "Language"
	},
	"ru" : {
		"map" : "Карта",
		"wlsinmap" : "КС на карте",
		"wallbreach" : "ТП вперёд",
		"farm" : "Фарм",
		"teleporter" : "Телепортер",
		"prophack" : "Взлом предметов",
		"openui" : "Открыть интерфейс",
		"spells" : "Заклинании",
		"fun" : "Веселье!",
		"wings" : "Крылья",
		"nowindwall" : "Убрать Ветер",
		"otherhacks" : "Другие взломы",
		"settings" : "Настройки",
		"currentmap" : "Карта",
		"semiautocr" : "Полу-авто Фарм Свечь",
		"tptowl" : "Телепорт к КС-у",
		"tpwltoy" : "Телепорт КС к себе",
		"tpsttoy" : "Телепорт всех статуй к себе",
		"collectwaxes" : "Собрать огоньки",
		"collectwls" : "Собрать весь Крылатый Свет",
		"unlockelders" : "Разблокировать Старейшин",
		"changemap" : "Сменить Карту",
		"goto" : "Идти...",
		"openui2" : "Открыть интерфейс",
		"closet" : "Гардероб",
		"constellation" : "Созвездие (с багом)",
		"funstuff" : "Весёлые вещи",
		"infinityfireworks" : "Бесконейный Фаерверк",
		"fakesleeping" : "Поддельный сон",
		"walkwithinstrument" : "Ходить с инструментом",
		"readchats" : "Читать чат",
		"wlcount" : "Количество КС",
		"setwlcount" : "Задать количество КС",
		"throwwl" : "Кидать КС⚠️",
		"explodewl" : "Взорвать КС ⚠️",
		"selecthacks" : "Выберите взломы",
		"autoburn" : "Автозажигание",
		"uacae" : "Разблок. Всех Одежд и Эмоции",
		"ufn" : "Разблок. Дружеских улучшений",
		"unlimitedenergy" : "Неограниченная энергия",
		"quicksteps" : "Очень Быстрый бег",
		"removeclouds" : "Убрать Облока",
		"wbd" : "Длина ТП вперёд",
		"uaiacr" : "Использовать Автозажигание во время фарма",
		"showpcoords" : "Показать Координаты игрока на гл.меню",
		"noproprecharge" : "Убрать перезарядку пердметов",
		"tpmenuaftercr" : "\"Телепорт\" меню после фарма",
		"ggvisible" : "Показать GG",
		"language" : "Язык"
	}
}